mdocfile/__init__.py
mdocfile/data_models.py
mdocfile/functions.py
mdocfile/utils.py
mdocfile-0.2.1.dist-info/METADATA
mdocfile-0.2.1.dist-info/WHEEL
mdocfile-0.2.1.dist-info/licenses/LICENSE
mdocfile-0.2.1.dist-info/RECORD
