Metadata-Version: 2.4
Name: mdocfile
Version: 0.2.1
Summary: SerialEM mdoc files as pandas dataframes.
Project-URL: homepage, https://github.com/teamtomo/mdocfile
Project-URL: repository, https://github.com/teamtomo/mdocfile
Author-email: Alister Burt <alisterburt@gmail.com>
License: BSD 3-Clause License
License-File: LICENSE
Classifier: Development Status :: 3 - Alpha
Classifier: License :: OSI Approved :: BSD License
Classifier: Natural Language :: English
Classifier: Programming Language :: Python :: 3
Classifier: Programming Language :: Python :: 3.9
Classifier: Programming Language :: Python :: 3.10
Classifier: Programming Language :: Python :: 3.11
Requires-Python: >=3.9
Requires-Dist: pandas
Requires-Dist: pydantic>=2
Provides-Extra: dev
Requires-Dist: black; extra == 'dev'
Requires-Dist: ipython; extra == 'dev'
Requires-Dist: mypy; extra == 'dev'
Requires-Dist: pdbpp; extra == 'dev'
Requires-Dist: pre-commit; extra == 'dev'
Requires-Dist: pytest; extra == 'dev'
Requires-Dist: pytest-cov; extra == 'dev'
Requires-Dist: rich; extra == 'dev'
Requires-Dist: ruff; extra == 'dev'
Provides-Extra: test
Requires-Dist: pytest-cov; extra == 'test'
Requires-Dist: pytest>=6.0; extra == 'test'
